pylendar/__init__.py
pylendar/pylendar.py
pylendar-0.4.0.dist-info/WHEEL
pylendar-0.4.0.dist-info/entry_points.txt
pylendar-0.4.0.dist-info/METADATA
pylendar-0.4.0.dist-info/RECORD
