Metadata-Version: 2.3
Name: pylendar
Version: 0.4.0
Summary: Python port of the calendar reminder utility commonly found on BSD-style systems, which displays upcoming relevant dates.
Author: Fredrik Mellström
Author-email: Fredrik Mellström <11281108+harkabeeparolus@users.noreply.github.com>
Requires-Dist: python-dateutil>=2.9.0.post0
Requires-Python: >=3.11
Project-URL: source, https://github.com/harkabeeparolus/pylendar
